gtsam_quadrics.cpython-36m-x86_64-linux-gnu.so
gtsam_quadrics.libs/libboost_atomic-b9e9eeed.so.1.79.0
gtsam_quadrics.libs/libboost_serialization-04382198.so.1.79.0
gtsam_quadrics.libs/libboost_filesystem-fec14429.so.1.79.0
gtsam_quadrics.libs/libboost_date_time-07525b69.so.1.79.0
gtsam_quadrics.libs/libboost_regex-a7ce2604.so.1.79.0
gtsam_quadrics.libs/libboost_thread-6a3f7314.so.1.79.0
gtsam_quadrics.libs/libboost_chrono-7e037afb.so.1.79.0
gtsam_quadrics.libs/libboost_timer-ece3e6e5.so.1.79.0
gtsam_quadrics.libs/libboost_system-8fe69198.so.1.79.0
gtsam/gtsam.cpython-36m-x86_64-linux-gnu.so
gtsam/noiseModel.py
gtsam/symbol_shorthand.py
gtsam/__init__.py
gtsam/imuBias.py
gtsam/specializations/sfm.h
gtsam/specializations/geometry.h
gtsam/specializations/sam.h
gtsam/specializations/slam.h
gtsam/specializations/base.h
gtsam/specializations/linear.h
gtsam/specializations/gtsam.h
gtsam/specializations/symbolic.h
gtsam/specializations/nonlinear.h
gtsam/specializations/navigation.h
gtsam/specializations/basis.h
gtsam/Data/pose3Localizationexample.txt
gtsam/Data/Plaza2_TD.txt
gtsam/Data/w20000.txt
gtsam/Data/VO_stereo_factors_large.txt
gtsam/Data/QPExample.QPS
gtsam/Data/Plaza2_.mat
gtsam/Data/toyExample.g2o
gtsam/Data/VO_camera_poses00.txt
gtsam/Data/simpleGraph10gradIter.txt
gtsam/Data/HS268.QPS
gtsam/Data/orientationsNoisyToyGraph.txt
gtsam/Data/dubrovnik-3-7-pre.txt
gtsam/Data/5pointExample2.txt
gtsam/Data/VO_calibration00s.txt
gtsam/Data/5pointExample1.txt
gtsam/Data/HS35MOD.QPS
gtsam/Data/18pointExample1.txt
gtsam/Data/toy3D.xml
gtsam/Data/Plaza1_TD.txt
gtsam/Data/Klaus3.g2o
gtsam/Data/optimizedNoisyToyGraph.txt
gtsam/Data/dubrovnik-3-7-18-pre.txt
gtsam/Data/KittiEquivBiasedImu.txt
gtsam/Data/KittiGps_converted.txt
gtsam/Data/example.graph
gtsam/Data/randomGrid3D.xml
gtsam/Data/Plaza1_.mat
gtsam/Data/HS51.QPS
gtsam/Data/sphere2500_groundtruth.txt
gtsam/Data/victoria_park.txt
gtsam/Data/HS21.QPS
gtsam_quadrics-0.3.0.dist-info/LICENSE.txt
gtsam_quadrics-0.3.0.dist-info/METADATA
gtsam_quadrics-0.3.0.dist-info/top_level.txt
gtsam_quadrics-0.3.0.dist-info/WHEEL
gtsam_quadrics-0.3.0.dist-info/RECORD
