Metadata-Version: 2.1
Name: gtsam-quadrics
Version: 0.3.0
Summary: Quadrics for GTSAM
Home-page: https://github.com/best-of-acrv/gtsam_quadrics
Author: Lachlan Nicholson
Author-email: lachlan.nicholson@hdr.qut.edu.au
Maintainer: Ben Talbot
Maintainer-email: b.talbot@qut.edu.au
License: UNKNOWN
Platform: UNKNOWN
Classifier: Development Status :: 4 - Beta
Classifier: Programming Language :: Python :: 3
Classifier: License :: OSI Approved :: BSD License
Classifier: Operating System :: OS Independent
License-File: LICENSE.txt
